grewritingpool/__init__.py
grewritingpool/main.py
grewritingpool-0.2.2.data/scripts/grewriting
grewritingpool-0.2.2.data/scripts/grewriting.cmd
grewritingpool-0.2.2.dist-info/LICENSE
grewritingpool-0.2.2.dist-info/METADATA
grewritingpool-0.2.2.dist-info/WHEEL
grewritingpool-0.2.2.dist-info/top_level.txt
grewritingpool-0.2.2.dist-info/RECORD
