Metadata-Version: 2.1
Name: grewritingpool
Version: 0.2.2
Summary: Helper for GRE Writing Pool
Home-page: https://github.com/patrick330602/grewritingpool
Author: Patrick Wu
Author-email: me@patrickwu.space
License: GPLv3
Keywords: gre,writing
Platform: UNKNOWN
Classifier: Environment :: Console
Classifier: Topic :: Education
Classifier: License :: OSI Approved :: GNU General Public License v3 (GPLv3)
Classifier: Operating System :: POSIX :: Linux
Classifier: Operating System :: Microsoft :: Windows
Classifier: Operating System :: MacOS :: MacOS X
Classifier: Programming Language :: Python :: 3 :: Only
Requires-Python: >=3.5
Requires-Dist: lxml
Requires-Dist: beautifulsoup4
Requires-Dist: requests
